indico_payment_paypal/__init__.py
indico_payment_paypal/blueprint.py
indico_payment_paypal/controllers.py
indico_payment_paypal/plugin.py
indico_payment_paypal/util.py
indico_payment_paypal/static/images/logo.png
indico_payment_paypal/templates/event_payment_form.html
indico_payment_paypal/templates/event_settings_encoding_warning.html
indico_payment_paypal/templates/transaction_details.html
indico_payment_paypal/translations/messages.pot
indico_payment_paypal/translations/cs_CZ/LC_MESSAGES/messages.mo
indico_payment_paypal/translations/cs_CZ/LC_MESSAGES/messages.po
indico_payment_paypal/translations/de_DE/LC_MESSAGES/messages.mo
indico_payment_paypal/translations/de_DE/LC_MESSAGES/messages.po
indico_payment_paypal/translations/en_CA/LC_MESSAGES/messages.mo
indico_payment_paypal/translations/en_CA/LC_MESSAGES/messages.po
indico_payment_paypal/translations/en_GB/LC_MESSAGES/messages.mo
indico_payment_paypal/translations/en_GB/LC_MESSAGES/messages.po
indico_payment_paypal/translations/es_ES/LC_MESSAGES/messages.mo
indico_payment_paypal/translations/es_ES/LC_MESSAGES/messages.po
indico_payment_paypal/translations/fr_FR/LC_MESSAGES/messages-js.po
indico_payment_paypal/translations/fr_FR/LC_MESSAGES/messages.mo
indico_payment_paypal/translations/fr_FR/LC_MESSAGES/messages.po
indico_payment_paypal/translations/hu_HU/LC_MESSAGES/messages.mo
indico_payment_paypal/translations/hu_HU/LC_MESSAGES/messages.po
indico_payment_paypal/translations/it_IT/LC_MESSAGES/messages.mo
indico_payment_paypal/translations/it_IT/LC_MESSAGES/messages.po
indico_payment_paypal/translations/ja_JP/LC_MESSAGES/messages.mo
indico_payment_paypal/translations/ja_JP/LC_MESSAGES/messages.po
indico_payment_paypal/translations/mn_MN/LC_MESSAGES/messages.mo
indico_payment_paypal/translations/mn_MN/LC_MESSAGES/messages.po
indico_payment_paypal/translations/pl_PL/LC_MESSAGES/messages.mo
indico_payment_paypal/translations/pl_PL/LC_MESSAGES/messages.po
indico_plugin_payment_paypal-3.3.2.dist-info/METADATA
indico_plugin_payment_paypal-3.3.2.dist-info/WHEEL
indico_plugin_payment_paypal-3.3.2.dist-info/entry_points.txt
indico_plugin_payment_paypal-3.3.2.dist-info/RECORD
